jupyter_databricks_kernel/__init__.py
jupyter_databricks_kernel/__main__.py
jupyter_databricks_kernel/_version.py
jupyter_databricks_kernel/config.py
jupyter_databricks_kernel/executor.py
jupyter_databricks_kernel/install.py
jupyter_databricks_kernel/kernel.py
jupyter_databricks_kernel/sync.py
jupyter_databricks_kernel-1.1.5.dist-info/METADATA
jupyter_databricks_kernel-1.1.5.dist-info/WHEEL
jupyter_databricks_kernel-1.1.5.dist-info/licenses/LICENSE
jupyter_databricks_kernel-1.1.5.dist-info/RECORD
