Metadata-Version: 2.4
Name: jupyter-databricks-kernel
Version: 1.1.5
Summary: A Jupyter kernel for complete remote execution on Databricks clusters
License-Expression: Apache-2.0
License-File: LICENSE
Classifier: Development Status :: 4 - Beta
Classifier: Framework :: Jupyter
Classifier: Intended Audience :: Developers
Classifier: License :: OSI Approved :: Apache Software License
Classifier: Operating System :: OS Independent
Classifier: Programming Language :: Python :: 3
Classifier: Programming Language :: Python :: 3.11
Classifier: Programming Language :: Python :: 3.12
Classifier: Programming Language :: Python :: 3.13
Requires-Python: >=3.11
Requires-Dist: databricks-sdk<1.0.0,>=0.30.0
Requires-Dist: ipykernel>=6.20.0
Requires-Dist: jupyter-client>=8.0.0
Requires-Dist: pathspec>=0.11.0
